<annotation>
	<folder></folder>
	<filename>2_jpg.rf.bef444a6ed5b7a0a04c843a6bbf02dcb.jpg</filename>
	<path>2_jpg.rf.bef444a6ed5b7a0a04c843a6bbf02dcb.jpg</path>
	<source>
		<database>roboflow.ai</database>
	</source>
	<size>
		<width>512</width>
		<height>512</height>
		<depth>3</depth>
	</size>
	<segmented>0</segmented>
	<object>
		<name>Oyster-Closed</name>
		<pose>Unspecified</pose>
		<truncated>0</truncated>
		<difficult>0</difficult>
		<occluded>0</occluded>
		<bndbox>
			<xmin>289</xmin>
			<xmax>487</xmax>
			<ymin>210</ymin>
			<ymax>349</ymax>
		</bndbox>
		<polygon>
			<x1>486.043781</x1>
			<y1>272.8</y1>
			<x2>483.199337</x2>
			<y2>246.666667</y2>
			<x3>476.799337</x3>
			<y3>243.733333</y3>
			<x4>454.754892</x4>
			<y4>243.2</y4>
			<x5>434.13267</x5>
			<y5>238.4</y5>
			<x6>417.777114</x6>
			<y6>233.066667</y6>
			<x7>402.843781</x7>
			<y7>226.933333</y7>
			<x8>387.199337</x8>
			<y8>221.066667</y8>
			<x9>372.977114</x9>
			<y9>216.266667</y9>
			<x10>354.488225</x10>
			<y10>211.733333</y10>
			<x11>335.288225</x11>
			<y11>209.333333</y11>
			<x12>311.466002</x12>
			<y12>223.733333</y12>
			<x13>305.066002</x13>
			<y13>235.2</y13>
			<x14>298.666002</x14>
			<y14>253.6</y14>
			<x15>292.621558</x15>
			<y15>274.933333</y15>
			<x16>288.354892</x16>
			<y16>337.6</y16>
			<x17>349.510447</x17>
			<y17>348</y17>
			<x18>393.599337</x18>
			<y18>343.2</y18>
			<x19>415.999337</x19>
			<y19>334.133333</y19>
			<x20>444.443781</x20>
			<y20>315.733333</y20>
			<x21>472.53267</x21>
			<y21>294.133333</y21>
			<x22>478.93267</x22>
			<y22>284</y22>
			<x23>486.043781</x23>
			<y23>272.8</y23>
		</polygon>
	</object>
	<object>
		<name>Oyster-Closed</name>
		<pose>Unspecified</pose>
		<truncated>0</truncated>
		<difficult>0</difficult>
		<occluded>0</occluded>
		<bndbox>
			<xmin>443</xmin>
			<xmax>508</xmax>
			<ymin>265</ymin>
			<ymax>355</ymax>
		</bndbox>
		<polygon>
			<x1>474.666667</x1>
			<y1>353.6</y1>
			<x2>507.377777</x2>
			<y2>341.866667</y2>
			<x3>503.822223</x3>
			<y3>264.266667</y3>
			<x4>478.933333</x4>
			<y4>281.866667</y4>
			<x5>472.888889</x5>
			<y5>293.6</y5>
			<x6>441.6</x6>
			<y6>318.4</y6>
			<x7>446.577777</x7>
			<y7>332.533333</y7>
			<x8>474.666667</x8>
			<y8>353.6</y8>
		</polygon>
	</object>
	<object>
		<name>Oyster-Open</name>
		<pose>Unspecified</pose>
		<truncated>0</truncated>
		<difficult>0</difficult>
		<occluded>0</occluded>
		<bndbox>
			<xmin>243</xmin>
			<xmax>460</xmax>
			<ymin>350</ymin>
			<ymax>414</ymax>
		</bndbox>
		<polygon>
			<x1>415.288889</x1>
			<y1>405.066667</y1>
			<x2>459.377777</x2>
			<y2>395.466667</y2>
			<x3>454.4</x3>
			<y3>363.466667</y3>
			<x4>390.4</x4>
			<y4>361.333333</y4>
			<x5>384</x5>
			<y5>357.6</y5>
			<x6>354.133333</x6>
			<y6>360.8</y6>
			<x7>347.022223</x7>
			<y7>353.333333</y7>
			<x8>267.377777</x8>
			<y8>349.066667</y8>
			<x9>241.777777</x9>
			<y9>367.2</y9>
			<x10>245.333333</x10>
			<y10>407.2</y10>
			<x11>347.022223</x11>
			<y11>413.066667</y11>
			<x12>415.288889</x12>
			<y12>405.066667</y12>
		</polygon>
	</object>
	<object>
		<name>Oyster-Closed</name>
		<pose>Unspecified</pose>
		<truncated>0</truncated>
		<difficult>0</difficult>
		<occluded>0</occluded>
		<bndbox>
			<xmin>477</xmin>
			<xmax>510</xmax>
			<ymin>346</ymin>
			<ymax>422</ymax>
		</bndbox>
		<polygon>
			<x1>509.155556</x1>
			<y1>344.8</y1>
			<x2>484.977777</x2>
			<y2>361.333333</y2>
			<x3>476.088889</x3>
			<y3>373.333333</y3>
			<x4>476.088889</x4>
			<y4>392.533333</y4>
			<x5>484.622223</x5>
			<y5>404</y5>
			<x6>503.111111</x6>
			<y6>420.8</y6>
			<x7>509.155556</x7>
			<y7>344.8</y7>
		</polygon>
	</object>
	<object>
		<name>Oyster-Closed</name>
		<pose>Unspecified</pose>
		<truncated>0</truncated>
		<difficult>0</difficult>
		<occluded>0</occluded>
		<bndbox>
			<xmin>12</xmin>
			<xmax>177</xmax>
			<ymin>380</ymin>
			<ymax>498</ymax>
		</bndbox>
		<polygon>
			<x1>11.377777</x1>
			<y1>423.2</y1>
			<x2>11.377777</x2>
			<y2>461.066667</y2>
			<x3>24.888889</x3>
			<y3>495.2</y3>
			<x4>63.288889</x4>
			<y4>496.8</y4>
			<x5>90.311111</x5>
			<y5>470.133333</y5>
			<x6>176.355556</x6>
			<y6>436.533333</y6>
			<x7>152.888889</x7>
			<y7>405.6</y7>
			<x8>83.911111</x8>
			<y8>378.933333</y8>
			<x9>17.066667</x9>
			<y9>400.8</y9>
			<x10>11.377777</x10>
			<y10>423.2</y10>
		</polygon>
	</object>
	<object>
		<name>Oyster-Closed</name>
		<pose>Unspecified</pose>
		<truncated>0</truncated>
		<difficult>0</difficult>
		<occluded>0</occluded>
		<bndbox>
			<xmin>66</xmin>
			<xmax>506</xmax>
			<ymin>413</ymin>
			<ymax>512</ymax>
		</bndbox>
		<polygon>
			<x1>417.422223</x1>
			<y1>429.333333</y1>
			<x2>402.844444</x2>
			<y2>414.4</y2>
			<x3>369.066667</x3>
			<y3>412</y3>
			<x4>317.866667</x4>
			<y4>416.8</y4>
			<x5>211.2</x5>
			<y5>425.866667</y5>
			<x6>160</x6>
			<y6>446.666667</y6>
			<x7>93.155556</x7>
			<y7>477.066667</y7>
			<x8>65.422223</x8>
			<y8>510.666667</y8>
			<x9>262.044444</x9>
			<y9>505.6</y9>
			<x10>504.533333</x10>
			<y10>507.2</y10>
			<x11>495.288889</x11>
			<y11>480.266667</y11>
			<x12>468.622223</x12>
			<y12>463.733333</y12>
			<x13>449.066667</x13>
			<y13>453.866667</y13>
			<x14>426.311111</x14>
			<y14>440.8</y14>
			<x15>417.422223</x15>
			<y15>429.333333</y15>
		</polygon>
	</object>
	<object>
		<name>Oyster-Closed</name>
		<pose>Unspecified</pose>
		<truncated>0</truncated>
		<difficult>0</difficult>
		<occluded>0</occluded>
		<bndbox>
			<xmin>1</xmin>
			<xmax>133</xmax>
			<ymin>1</ymin>
			<ymax>118</ymax>
		</bndbox>
		<polygon>
			<x1>93.155556</x1>
			<y1>25.333333</y1>
			<x2>78.577777</x2>
			<y2>2.133333</y2>
			<x3>7.111111</x3>
			<y3>0.266667</y3>
			<x4>0</x4>
			<y4>24.266667</y4>
			<x5>30.577777</x5>
			<y5>45.6</y5>
			<x6>40.888889</x6>
			<y6>61.866667</y6>
			<x7>53.688889</x7>
			<y7>76.266667</y7>
			<x8>68.622223</x8>
			<y8>89.866667</y8>
			<x9>87.111111</x9>
			<y9>97.333333</y9>
			<x10>131.555556</x10>
			<y10>116.533333</y10>
			<x11>118.044444</x11>
			<y11>86.133333</y11>
			<x12>112</x12>
			<y12>68</y12>
			<x13>105.6</x13>
			<y13>54.933333</y13>
			<x14>99.555556</x14>
			<y14>42.666667</y14>
			<x15>93.155556</x15>
			<y15>25.333333</y15>
		</polygon>
	</object>
	<object>
		<name>Oyster-Closed</name>
		<pose>Unspecified</pose>
		<truncated>0</truncated>
		<difficult>0</difficult>
		<occluded>0</occluded>
		<bndbox>
			<xmin>153</xmin>
			<xmax>263</xmax>
			<ymin>8</ymin>
			<ymax>125</ymax>
		</bndbox>
		<polygon>
			<x1>235.377777</x1>
			<y1>80</y1>
			<x2>228.622223</x2>
			<y2>68.8</y2>
			<x3>222.577777</x3>
			<y3>55.466667</y3>
			<x4>215.822223</x4>
			<y4>42.933333</y4>
			<x5>208</x5>
			<y5>31.466667</y5>
			<x6>199.822223</x6>
			<y6>20.533333</y6>
			<x7>182.4</x7>
			<y7>8</y7>
			<x8>169.6</x8>
			<y8>6.666667</y8>
			<x9>152.177777</x9>
			<y9>29.066667</y9>
			<x10>159.288889</x10>
			<y10>42.133333</y10>
			<x11>165.688889</x11>
			<y11>52.266667</y11>
			<x12>171.733333</x12>
			<y12>62.933333</y12>
			<x13>179.2</x13>
			<y13>73.866667</y13>
			<x14>187.733333</x14>
			<y14>85.6</y14>
			<x15>205.511111</x15>
			<y15>102.666667</y15>
			<x16>238.577777</x16>
			<y16>124.266667</y16>
			<x17>261.688889</x17>
			<y17>117.866667</y17>
			<x18>254.222223</x18>
			<y18>104.8</y18>
			<x19>242.488889</x19>
			<y19>91.466667</y19>
			<x20>235.377777</x20>
			<y20>80</y20>
		</polygon>
	</object>
	<object>
		<name>Oyster-Closed</name>
		<pose>Unspecified</pose>
		<truncated>0</truncated>
		<difficult>0</difficult>
		<occluded>0</occluded>
		<bndbox>
			<xmin>2</xmin>
			<xmax>72</xmax>
			<ymin>82</ymin>
			<ymax>170</ymax>
		</bndbox>
		<polygon>
			<x1>51.911775</x1>
			<y1>168.8</y1>
			<x2>71.111775</x2>
			<y2>160</y2>
			<x3>67.200663</x3>
			<y3>128.8</y3>
			<x4>58.66733</x4>
			<y4>116.8</y4>
			<x5>40.533998</x5>
			<y5>98.4</y5>
			<x6>20.26733</x6>
			<y6>84</y6>
			<x7>1.422886</x7>
			<y7>81.066667</y7>
			<x8>6.400663</x8>
			<y8>159.733333</y8>
			<x9>30.578442</x9>
			<y9>163.733333</y9>
			<x10>51.911775</x10>
			<y10>168.8</y10>
		</polygon>
	</object>
	<object>
		<name>Oyster-Closed</name>
		<pose>Unspecified</pose>
		<truncated>0</truncated>
		<difficult>0</difficult>
		<occluded>0</occluded>
		<bndbox>
			<xmin>146</xmin>
			<xmax>259</xmax>
			<ymin>208</ymin>
			<ymax>319</ymax>
		</bndbox>
		<polygon>
			<x1>243.555556</x1>
			<y1>263.466667</y1>
			<x2>250.666667</x2>
			<y2>252.266667</y2>
			<x3>257.066667</x3>
			<y3>240.533333</y3>
			<x4>257.777777</x4>
			<y4>209.6</y4>
			<x5>235.377777</x5>
			<y5>207.466667</y5>
			<x6>207.644444</x6>
			<y6>213.066667</y6>
			<x7>182.4</x7>
			<y7>232.533333</y7>
			<x8>166.755556</x8>
			<y8>237.6</y8>
			<x9>150.755556</x9>
			<y9>247.733333</y9>
			<x10>145.066667</x10>
			<y10>285.333333</y10>
			<x11>168.888889</x11>
			<y11>308.266667</y11>
			<x12>188.444444</x12>
			<y12>317.6</y12>
			<x13>214.4</x13>
			<y13>306.133333</y13>
			<x14>222.933333</x14>
			<y14>294.4</y14>
			<x15>230.044444</x15>
			<y15>284.266667</y15>
			<x16>236.444444</x16>
			<y16>273.866667</y16>
			<x17>243.555556</x17>
			<y17>263.466667</y17>
		</polygon>
	</object>
</annotation>
