<annotation>
	<folder></folder>
	<filename>318_png_jpg.rf.ed86abbcaac76bf13c160529c2d78204.jpg</filename>
	<path>318_png_jpg.rf.ed86abbcaac76bf13c160529c2d78204.jpg</path>
	<source>
		<database>roboflow.ai</database>
	</source>
	<size>
		<width>512</width>
		<height>512</height>
		<depth>3</depth>
	</size>
	<segmented>0</segmented>
	<object>
		<name>Oyster-Closed</name>
		<pose>Unspecified</pose>
		<truncated>0</truncated>
		<difficult>0</difficult>
		<occluded>0</occluded>
		<bndbox>
			<xmin>297</xmin>
			<xmax>343</xmax>
			<ymin>108</ymin>
			<ymax>171</ymax>
		</bndbox>
		<polygon>
			<x1>337.735895</x1>
			<y1>155.939087</y1>
			<x2>342.155659</x2>
			<y2>125.617598</y2>
			<x3>323.003344</x3>
			<y3>106.847152</y3>
			<x4>296.484754</x4>
			<y4>106.847152</y4>
			<x5>296.484754</x5>
			<y5>138.612522</y5>
			<x6>296.484754</x6>
			<y6>148.719684</y6>
			<x7>305.60737</x7>
			<y7>170.37789</y7>
			<x8>337.735895</x8>
			<y8>155.939087</y8>
		</polygon>
	</object>
	<object>
		<name>Oyster-Closed</name>
		<pose>Unspecified</pose>
		<truncated>0</truncated>
		<difficult>0</difficult>
		<occluded>0</occluded>
		<bndbox>
			<xmin>446</xmin>
			<xmax>507</xmax>
			<ymin>119</ymin>
			<ymax>189</ymax>
		</bndbox>
		<polygon>
			<x1>445.283514</x1>
			<y1>183.372815</y1>
			<x2>473.275359</x2>
			<y2>187.704455</y2>
			<x3>490.954418</x3>
			<y3>164.602369</y3>
			<x4>505.68697</x4>
			<y4>147.275803</y4>
			<x5>495.374185</x5>
			<y5>121.285956</y5>
			<x6>486.534655</x6>
			<y6>118.398194</y6>
			<x7>451.176533</x7>
			<y7>140.056402</y7>
			<x8>445.283514</x8>
			<y8>183.372815</y8>
		</polygon>
	</object>
	<object>
		<name>Oyster-Closed</name>
		<pose>Unspecified</pose>
		<truncated>0</truncated>
		<difficult>0</difficult>
		<occluded>0</occluded>
		<bndbox>
			<xmin>233</xmin>
			<xmax>312</xmax>
			<ymin>173</ymin>
			<ymax>226</ymax>
		</bndbox>
		<polygon>
			<x1>280.278949</x1>
			<y1>225.245346</y1>
			<x2>309.744048</x2>
			<y2>203.587141</y2>
			<x3>311.217303</x3>
			<y3>183.372815</y3>
			<x4>272.912673</x4>
			<y4>171.821771</y4>
			<x5>243.447572</x5>
			<y5>173.26565</y5>
			<x6>231.661531</x6>
			<y6>183.372815</y6>
			<x7>265.546398</x7>
			<y7>200.699378</y7>
			<x8>275.859183</x8>
			<y8>218.025945</y8>
			<x9>280.278949</x9>
			<y9>225.245346</y9>
		</polygon>
	</object>
	<object>
		<name>Oyster-Closed</name>
		<pose>Unspecified</pose>
		<truncated>0</truncated>
		<difficult>0</difficult>
		<occluded>0</occluded>
		<bndbox>
			<xmin>211</xmin>
			<xmax>278</xmax>
			<ymin>193</ymin>
			<ymax>277</ymax>
		</bndbox>
		<polygon>
			<x1>259.653377</x1>
			<y1>265.673999</y1>
			<x2>277.332438</x2>
			<y2>231.020869</y2>
			<x3>258.180123</x3>
			<y3>199.255499</y3>
			<x4>234.608042</x4>
			<y4>192.036097</y4>
			<x5>216.92898</x5>
			<y5>215.138185</y5>
			<x6>209.562706</x6>
			<y6>238.240271</y6>
			<x7>225.768512</x7>
			<y7>275.781162</y7>
			<x8>259.653377</x8>
			<y8>265.673999</y8>
		</polygon>
	</object>
	<object>
		<name>Oyster-Closed</name>
		<pose>Unspecified</pose>
		<truncated>0</truncated>
		<difficult>0</difficult>
		<occluded>0</occluded>
		<bndbox>
			<xmin>306</xmin>
			<xmax>513</xmax>
			<ymin>177</ymin>
			<ymax>323</ymax>
		</bndbox>
		<polygon>
			<x1>512</x1>
			<y1>196.311434</y1>
			<x2>432.024218</x2>
			<y2>192.036097</y2>
			<x3>378.987036</x3>
			<y3>189.148337</y3>
			<x4>345.10217</x4>
			<y4>176.153413</y4>
			<x5>311.217303</x5>
			<y5>206.474901</y5>
			<x6>308.270794</x6>
			<y6>228.133108</y6>
			<x7>305.324284</x7>
			<y7>236.79639</y7>
			<x8>356.88821</x8>
			<y8>308.990412</y8>
			<x9>427.604452</x9>
			<y9>321.985335</y9>
			<x10>501.267205</x10>
			<y10>316.209813</y10>
			<x11>512</x11>
			<y11>311.90667</y11>
			<x12>512</x12>
			<y12>196.311434</y12>
		</polygon>
	</object>
</annotation>
