<annotation>
	<folder></folder>
	<filename>34_jpg.rf.c40057cb455c50e6455bce4200b321b6.jpg</filename>
	<path>34_jpg.rf.c40057cb455c50e6455bce4200b321b6.jpg</path>
	<source>
		<database>roboflow.ai</database>
	</source>
	<size>
		<width>512</width>
		<height>512</height>
		<depth>3</depth>
	</size>
	<segmented>0</segmented>
	<object>
		<name>Oyster-Closed</name>
		<pose>Unspecified</pose>
		<truncated>0</truncated>
		<difficult>0</difficult>
		<occluded>0</occluded>
		<bndbox>
			<xmin>250</xmin>
			<xmax>508</xmax>
			<ymin>205</ymin>
			<ymax>343</ymax>
		</bndbox>
		<polygon>
			<x1>325.33267</x1>
			<y1>303.2</y1>
			<x2>339.910447</x2>
			<y2>321.333333</y2>
			<x3>359.110447</x3>
			<y3>332.8</y3>
			<x4>377.599337</x4>
			<y4>337.6</y4>
			<x5>411.73267</x5>
			<y5>342.133333</y5>
			<x6>436.621558</x6>
			<y6>338.4</y6>
			<x7>452.621558</x7>
			<y7>332.8</y7>
			<x8>469.688225</x8>
			<y8>326.4</y8>
			<x9>500.977114</x9>
			<y9>301.333333</y9>
			<x10>507.377114</x10>
			<y10>271.733333</y10>
			<x11>505.954892</x11>
			<y11>223.466667</y11>
			<x12>490.310447</x12>
			<y12>216.8</y12>
			<x13>473.954892</x13>
			<y13>211.733333</y13>
			<x14>452.621558</x14>
			<y14>206.133333</y14>
			<x15>411.021558</x15>
			<y15>204.266667</y15>
			<x16>375.821558</x16>
			<y16>209.066667</y16>
			<x17>362.310447</x17>
			<y17>213.6</y17>
			<x18>346.310447</x18>
			<y18>222.133333</y18>
			<x19>325.688225</x19>
			<y19>238.4</y19>
			<x20>308.621558</x20>
			<y20>246.666667</y20>
			<x21>292.266002</x21>
			<y21>253.866667</y21>
			<x22>274.843781</x22>
			<y22>259.2</y22>
			<x23>259.910447</x23>
			<y23>264.533333</y23>
			<x24>248.53267</x24>
			<y24>281.866667</y24>
			<x25>262.399337</x25>
			<y25>293.333333</y25>
			<x26>292.977114</x26>
			<y26>298.133333</y26>
			<x27>325.33267</x27>
			<y27>303.2</y27>
		</polygon>
	</object>
	<object>
		<name>Oyster-Closed</name>
		<pose>Unspecified</pose>
		<truncated>0</truncated>
		<difficult>0</difficult>
		<occluded>0</occluded>
		<bndbox>
			<xmin>56</xmin>
			<xmax>241</xmax>
			<ymin>223</ymin>
			<ymax>328</ymax>
		</bndbox>
		<polygon>
			<x1>237.156884</x1>
			<y1>275.466667</y1>
			<x2>230.756884</x2>
			<y2>262.133333</y2>
			<x3>224.712438</x3>
			<y3>249.6</y3>
			<x4>203.734661</x4>
			<y4>237.333333</y4>
			<x5>185.956884</x5>
			<y5>232.533333</y5>
			<x6>162.490217</x6>
			<y6>227.733333</y6>
			<x7>121.245772</x7>
			<y7>223.2</y7>
			<x8>109.867994</x8>
			<y8>222.4</y8>
			<x9>83.556884</x9>
			<y9>228.266667</y9>
			<x10>67.201328</x10>
			<y10>236.266667</y10>
			<x11>55.467994</x11>
			<y11>258.4</y11>
			<x12>83.912438</x12>
			<y12>278.133333</y12>
			<x13>110.934661</x13>
			<y13>297.6</y13>
			<x14>127.645772</x14>
			<y14>313.066667</y14>
			<x15>142.22355</x15>
			<y15>327.466667</y15>
			<x16>185.245772</x16>
			<y16>323.733333</y16>
			<x17>202.312438</x17>
			<y17>315.466667</y17>
			<x18>223.290217</x18>
			<y18>304.533333</y18>
			<x19>240.356884</x19>
			<y19>295.733333</y19>
			<x20>237.156884</x20>
			<y20>275.466667</y20>
		</polygon>
	</object>
	<object>
		<name>Oyster-Closed</name>
		<pose>Unspecified</pose>
		<truncated>0</truncated>
		<difficult>0</difficult>
		<occluded>0</occluded>
		<bndbox>
			<xmin>125</xmin>
			<xmax>393</xmax>
			<ymin>1</ymin>
			<ymax>66</ymax>
		</bndbox>
		<polygon>
			<x1>179.2</x1>
			<y1>46.133333</y1>
			<x2>285.155556</x2>
			<y2>65.333333</y2>
			<x3>334.933333</x3>
			<y3>62.666667</y3>
			<x4>385.422223</x4>
			<y4>8.8</y4>
			<x5>391.822223</x5>
			<y5>1.866667</y5>
			<x6>124.088889</x6>
			<y6>0</y6>
			<x7>135.822223</x7>
			<y7>54.133333</y7>
			<x8>179.2</x8>
			<y8>46.133333</y8>
		</polygon>
	</object>
	<object>
		<name>Oyster-Closed</name>
		<pose>Unspecified</pose>
		<truncated>0</truncated>
		<difficult>0</difficult>
		<occluded>0</occluded>
		<bndbox>
			<xmin>2</xmin>
			<xmax>132</xmax>
			<ymin>261</ymin>
			<ymax>425</ymax>
		</bndbox>
		<polygon>
			<x1>97.777777</x1>
			<y1>287.466667</y1>
			<x2>72.533333</x2>
			<y2>270.933333</y2>
			<x3>58.311111</x3>
			<y3>265.333333</y3>
			<x4>41.244444</x4>
			<y4>260.533333</y4>
			<x5>2.133333</x5>
			<y5>260</y5>
			<x6>0.711111</x6>
			<y6>340</y6>
			<x7>6.755556</x7>
			<y7>410.666667</y7>
			<x8>13.511111</x8>
			<y8>423.733333</y8>
			<x9>35.911111</x9>
			<y9>423.2</y9>
			<x10>51.2</x10>
			<y10>408</y10>
			<x11>60.088889</x11>
			<y11>394.666667</y11>
			<x12>76.088889</x12>
			<y12>381.866667</y12>
			<x13>93.511111</x13>
			<y13>372.533333</y13>
			<x14>120.533333</x14>
			<y14>354.666667</y14>
			<x15>131.2</x15>
			<y15>336.533333</y15>
			<x16>125.155556</x16>
			<y16>305.333333</y16>
			<x17>97.777777</x17>
			<y17>287.466667</y17>
		</polygon>
	</object>
	<object>
		<name>Oyster-Closed</name>
		<pose>Unspecified</pose>
		<truncated>0</truncated>
		<difficult>0</difficult>
		<occluded>0</occluded>
		<bndbox>
			<xmin>72</xmin>
			<xmax>333</xmax>
			<ymin>312</ymin>
			<ymax>513</ymax>
		</bndbox>
		<polygon>
			<x1>228.266667</x1>
			<y1>509.6</y1>
			<x2>238.933333</x2>
			<y2>483.733333</y2>
			<x3>246.755556</x3>
			<y3>473.066667</y3>
			<x4>254.222223</x4>
			<y4>462.133333</y4>
			<x5>266.311111</x5>
			<y5>448.533333</y5>
			<x6>280.177777</x6>
			<y6>433.6</y6>
			<x7>290.133333</x7>
			<y7>420</y7>
			<x8>304</x8>
			<y8>404.266667</y8>
			<x9>315.733333</x9>
			<y9>389.6</y9>
			<x10>325.333333</x10>
			<y10>375.466667</y10>
			<x11>331.733333</x11>
			<y11>362.133333</y11>
			<x12>321.066667</x12>
			<y12>315.466667</y12>
			<x13>266.666667</x13>
			<y13>310.933333</y13>
			<x14>216.888889</x14>
			<y14>315.733333</y14>
			<x15>197.688889</x15>
			<y15>321.866667</y15>
			<x16>179.911111</x16>
			<y16>330.666667</y16>
			<x17>156.444444</x17>
			<y17>350.933333</y17>
			<x18>137.244444</x18>
			<y18>369.333333</y18>
			<x19>127.644444</x19>
			<y19>383.2</y19>
			<x20>82.488889</x20>
			<y20>402.933333</y20>
			<x21>71.111111</x21>
			<y21>459.466667</y21>
			<x22>78.933333</x22>
			<y22>483.466667</y22>
			<x23>115.2</x23>
			<y23>511.733333</y23>
			<x24>158.577777</x24>
			<y24>509.066667</y24>
			<x25>228.266667</x25>
			<y25>509.6</y25>
		</polygon>
	</object>
	<object>
		<name>Oyster-Closed</name>
		<pose>Unspecified</pose>
		<truncated>0</truncated>
		<difficult>0</difficult>
		<occluded>0</occluded>
		<bndbox>
			<xmin>235</xmin>
			<xmax>498</xmax>
			<ymin>440</ymin>
			<ymax>512</ymax>
		</bndbox>
		<polygon>
			<x1>321.778442</x1>
			<y1>446.666667</y1>
			<x2>253.511775</x2>
			<y2>472.8</y2>
			<x3>233.600663</x3>
			<y3>510.133333</y3>
			<x4>477.511775</x4>
			<y4>511.2</y4>
			<x5>496.711775</x5>
			<y5>471.733333</y5>
			<x6>382.222886</x6>
			<y6>438.666667</y6>
			<x7>321.778442</x7>
			<y7>446.666667</y7>
		</polygon>
	</object>
	<object>
		<name>Oyster-Closed</name>
		<pose>Unspecified</pose>
		<truncated>0</truncated>
		<difficult>0</difficult>
		<occluded>0</occluded>
		<bndbox>
			<xmin>403</xmin>
			<xmax>513</xmax>
			<ymin>4</ymin>
			<ymax>116</ymax>
		</bndbox>
		<polygon>
			<x1>401.777777</x1>
			<y1>67.466667</y1>
			<x2>413.866667</x2>
			<y2>76</y2>
			<x3>432.355556</x3>
			<y3>82.933333</y3>
			<x4>481.422223</x4>
			<y4>106.4</y4>
			<x5>511.644444</x5>
			<y5>115.466667</y5>
			<x6>511.644444</x6>
			<y6>6.666667</y6>
			<x7>493.511111</x7>
			<y7>2.933333</y7>
			<x8>460.8</x8>
			<y8>10.4</y8>
			<x9>428.088889</x9>
			<y9>29.066667</y9>
			<x10>401.777777</x10>
			<y10>67.466667</y10>
		</polygon>
	</object>
	<object>
		<name>Oyster-Closed</name>
		<pose>Unspecified</pose>
		<truncated>0</truncated>
		<difficult>0</difficult>
		<occluded>0</occluded>
		<bndbox>
			<xmin>277</xmin>
			<xmax>451</xmax>
			<ymin>67</ymin>
			<ymax>206</ymax>
		</bndbox>
		<polygon>
			<x1>439.466667</x1>
			<y1>140.533333</y1>
			<x2>435.2</x2>
			<y2>106.933333</y2>
			<x3>424.533333</x3>
			<y3>82.4</y3>
			<x4>376.888889</x4>
			<y4>66.4</y4>
			<x5>332.088889</x5>
			<y5>66.4</y5>
			<x6>297.955556</x6>
			<y6>72.266667</y6>
			<x7>275.911111</x7>
			<y7>70.666667</y7>
			<x8>281.6</x8>
			<y8>83.466667</y8>
			<x9>289.422223</x9>
			<y9>102.133333</y9>
			<x10>307.2</x10>
			<y10>112.8</y10>
			<x11>347.022223</x11>
			<y11>112.8</y11>
			<x12>380.444444</x12>
			<y12>127.733333</y12>
			<x13>411.733333</x13>
			<y13>161.866667</y13>
			<x14>433.777777</x14>
			<y14>173.066667</y14>
			<x15>445.866667</x15>
			<y15>203.466667</y15>
			<x16>450.133333</x16>
			<y16>204.533333</y16>
			<x17>448.711111</x17>
			<y17>168.8</y17>
			<x18>439.466667</x18>
			<y18>140.533333</y18>
		</polygon>
	</object>
	<object>
		<name>Oyster-Closed</name>
		<pose>Unspecified</pose>
		<truncated>0</truncated>
		<difficult>0</difficult>
		<occluded>0</occluded>
		<bndbox>
			<xmin>1</xmin>
			<xmax>302</xmax>
			<ymin>57</ymin>
			<ymax>223</ymax>
		</bndbox>
		<polygon>
			<x1>217.955556</x1>
			<y1>153.6</y1>
			<x2>233.6</x2>
			<y2>148.533333</y2>
			<x3>265.955556</x3>
			<y3>144</y3>
			<x4>289.422223</x4>
			<y4>132</y4>
			<x5>298.311111</x5>
			<y5>123.2</y5>
			<x6>301.155556</x6>
			<y6>111.2</y6>
			<x7>285.155556</x7>
			<y7>105.066667</y7>
			<x8>280.888889</x8>
			<y8>98.4</y8>
			<x9>282.311111</x9>
			<y9>92</y9>
			<x10>271.644444</x10>
			<y10>83.466667</y10>
			<x11>268.444444</x11>
			<y11>73.333333</y11>
			<x12>250.311111</x12>
			<y12>67.733333</y12>
			<x13>233.6</x13>
			<y13>62.4</y13>
			<x14>207.644444</x14>
			<y14>57.866667</y14>
			<x15>155.733333</x15>
			<y15>56.266667</y15>
			<x16>119.466667</x16>
			<y16>61.066667</y16>
			<x17>95.288889</x17>
			<y17>65.6</y17>
			<x18>25.6</x18>
			<y18>69.866667</y18>
			<x19>0</x19>
			<y19>81.333333</y19>
			<x20>2.133333</x20>
			<y20>109.6</y20>
			<x21>2.844444</x21>
			<y21>221.6</y21>
			<x22>59.022223</x22>
			<y22>220</y22>
			<x23>118.755556</x23>
			<y23>206.666667</y23>
			<x24>143.288889</x24>
			<y24>201.866667</y24>
			<x25>161.066667</x25>
			<y25>197.066667</y25>
			<x26>180.266667</x26>
			<y26>178.133333</y26>
			<x27>217.955556</x27>
			<y27>153.6</y27>
		</polygon>
	</object>
	<object>
		<name>Oyster-Open</name>
		<pose>Unspecified</pose>
		<truncated>0</truncated>
		<difficult>0</difficult>
		<occluded>0</occluded>
		<bndbox>
			<xmin>296</xmin>
			<xmax>355</xmax>
			<ymin>217</ymin>
			<ymax>254</ymax>
		</bndbox>
		<polygon>
			<x1>295.415831</x1>
			<y1>253.333333</y1>
			<x2>329.180996</x2>
			<y2>250.666667</y2>
			<x3>354.06059</x3>
			<y3>233.333333</y3>
			<x4>350.506362</x4>
			<y4>216</y4>
			<x5>300.747173</x5>
			<y5>232</y5>
			<x6>295.415831</x6>
			<y6>253.333333</y6>
		</polygon>
	</object>
</annotation>
