<annotation>
	<folder></folder>
	<filename>7006_jpg.rf.0f3452ee9a00d5cd16da426d0dbc17d1.jpg</filename>
	<path>7006_jpg.rf.0f3452ee9a00d5cd16da426d0dbc17d1.jpg</path>
	<source>
		<database>roboflow.ai</database>
	</source>
	<size>
		<width>512</width>
		<height>512</height>
		<depth>3</depth>
	</size>
	<segmented>0</segmented>
	<object>
		<name>Oyster-Closed</name>
		<pose>Unspecified</pose>
		<truncated>0</truncated>
		<difficult>0</difficult>
		<occluded>0</occluded>
		<bndbox>
			<xmin>28</xmin>
			<xmax>513</xmax>
			<ymin>87</ymin>
			<ymax>513</ymax>
		</bndbox>
		<polygon>
			<x1>408.711111</x1>
			<y1>512</y1>
			<x2>454.044444</x2>
			<y2>511.2</y2>
			<x3>496</x3>
			<y3>511.2</y3>
			<x4>509.511111</x4>
			<y4>504.8</y4>
			<x5>511.644444</x5>
			<y5>267.466667</y5>
			<x6>501.688889</x6>
			<y6>257.866667</y6>
			<x7>480.355556</x7>
			<y7>228.533333</y7>
			<x8>449.777778</x8>
			<y8>199.733333</y8>
			<x9>422.044444</x9>
			<y9>170.933333</y9>
			<x10>377.955556</x10>
			<y10>154.4</y10>
			<x11>348.8</x11>
			<y11>138.933333</y11>
			<x12>320.355556</x12>
			<y12>118.133333</y12>
			<x13>304.711111</x13>
			<y13>97.333333</y13>
			<x14>262.755556</x14>
			<y14>85.6</y14>
			<x15>226.488889</x15>
			<y15>93.6</y15>
			<x16>174.577778</x16>
			<y16>91.466667</y16>
			<x17>97.066667</x17>
			<y17>101.6</y17>
			<x18>87.111111</x18>
			<y18>124.533333</y18>
			<x19>70.755556</x19>
			<y19>167.2</y19>
			<x20>72.177778</x20>
			<y20>190.666667</y20>
			<x21>62.222222</x21>
			<y21>194.933333</y21>
			<x22>40.888889</x22>
			<y22>221.066667</y22>
			<x23>32</x23>
			<y23>250.933333</y23>
			<x24>27.022222</x24>
			<y24>276.533333</y24>
			<x25>32.711111</x25>
			<y25>298.4</y25>
			<x26>36.977778</x26>
			<y26>319.733333</y26>
			<x27>83.911111</x27>
			<y27>353.866667</y27>
			<x28>117.688889</x28>
			<y28>386.4</y28>
			<x29>171.733333</x29>
			<y29>408.266667</y29>
			<x30>193.777778</x30>
			<y30>432.8</y30>
			<x31>234.311111</x31>
			<y31>457.866667</y31>
			<x32>308.266667</x32>
			<y32>483.466667</y32>
			<x33>336</x33>
			<y33>492.533333</y33>
			<x34>368.711111</x34>
			<y34>501.6</y34>
			<x35>392.977778</x35>
			<y35>512</y35>
			<x36>408.711111</x36>
			<y36>512</y36>
		</polygon>
	</object>
</annotation>
